setup.py
distributions_luna_version/Binomialdistribution.py
distributions_luna_version/Gaussiandistribution.py
distributions_luna_version/Generaldistribution.py
distributions_luna_version/__init__.py
distributions_luna_version.egg-info/PKG-INFO
distributions_luna_version.egg-info/SOURCES.txt
distributions_luna_version.egg-info/dependency_links.txt
distributions_luna_version.egg-info/not-zip-safe
distributions_luna_version.egg-info/top_level.txt