Metadata-Version: 1.0
Name: distributions-luna-version
Version: 1.0
Summary: Gaussian and Binomial distributions
Home-page: UNKNOWN
Author: Yuemin Li
Author-email: cloverlym@gmail.com
License: UNKNOWN
Platform: UNKNOWN
